storage/__init__.py
common_storage-0.0.1.dist-info/LICENSE
common_storage-0.0.1.dist-info/METADATA
common_storage-0.0.1.dist-info/WHEEL
common_storage-0.0.1.dist-info/top_level.txt
common_storage-0.0.1.dist-info/RECORD
